[
  {
    "id": 1,
    "filename": "img1.jpeg",
    "caption": "Annual Community Gathering",
    "category": "events"
  },
  {
    "id": 2,
    "filename": "img2.jpeg",
    "caption": "Annual Community Gathering",
    "category": "events"
  },
  {
    "id": 3,
    "filename": "img3.jpeg",
    "caption": "Annual Community Gathering",
    "category": "events"
  },
  {
    "id": 4,
    "filename": "img4.jpeg",
    "caption": "Annual Community Gathering",
    "category": "events"
  },
  {
    "id": 5,
    "filename": "img5.jpeg",
    "caption": "Annual Community Gathering",
    "category": "events"
  },
  {
    "id": 6,
    "filename": "img6.jpeg",
    "caption": "Annual Community Gathering",
    "category": "events"
  },
  {
    "id": 7,
    "filename": "img7.jpeg",
    "caption": "Annual Community Gathering",
    "category": "events"
  }
]
